taskiq_memphis/__init__.py
taskiq_memphis/broker.py
taskiq_memphis/exceptions.py
taskiq_memphis/models.py
taskiq_memphis-0.2.0.dist-info/LICENSE
taskiq_memphis-0.2.0.dist-info/METADATA
taskiq_memphis-0.2.0.dist-info/WHEEL
taskiq_memphis-0.2.0.dist-info/RECORD
